SplatStats/Battle.py
SplatStats/Player.py
SplatStats/StatInk.py
SplatStats/Team.py
SplatStats/__init__.py
SplatStats/_version.py
SplatStats/auxiliary.py
SplatStats/colors.py
SplatStats/constants.py
SplatStats/files.py
SplatStats/parsers.py
SplatStats/plots.py
SplatStats/plotsAux.py
SplatStats/plotsTeam.py
SplatStats/statInkConstants.py
SplatStats/statInkPlots.py
SplatStats/statInkStats.py
SplatStats/stats.py
SplatStats-6.0.0.dist-info/LICENSE
SplatStats-6.0.0.dist-info/METADATA
SplatStats-6.0.0.dist-info/WHEEL
SplatStats-6.0.0.dist-info/top_level.txt
SplatStats-6.0.0.dist-info/RECORD
