Metadata-Version: 2.1
Name: SplatStats
Version: 6.0.0
Home-page: https://github.com/Chipdelmal/SplatStats
Author: chipdelmal
Author-email: chipdelmal@gmail.com
License: GPLv3
Classifier: Programming Language :: Python :: 3.10
Classifier: Operating System :: OS Independent
Requires-Python: >=3.10
License-File: LICENSE
Requires-Dist: dill
Requires-Dist: termcolor
Requires-Dist: colorutils
Requires-Dist: tqdm
Requires-Dist: numpy
Requires-Dist: scipy
Requires-Dist: pandas
Requires-Dist: scikit-learn
Requires-Dist: DateTimeRange
Requires-Dist: matplotlib
Requires-Dist: pywaffle
Requires-Dist: squarify
Requires-Dist: seaborn
Provides-Extra: dev
Requires-Dist: twine ; extra == 'dev'
Requires-Dist: wheel ; extra == 'dev'
Requires-Dist: sphinx ; extra == 'dev'
Requires-Dist: sphinx-press-theme ; extra == 'dev'
